{"event_id": 0, "timestamp": "2025-11-09T16:27:59.954998", "event_type": "TOPOLOGY_CREATED", "simulation_id": "20251109_162759", "topology_type": "linear", "data": {"topology_type": "linear", "num_routers": 5, "description": "Линейная цепочка маршрутизаторов"}}
{"event_id": 1, "timestamp": "2025-11-09T16:27:59.955644", "event_type": "ROUTER_ADDED", "simulation_id": "20251109_162759", "router_id": -1, "data": {"router_id": -1, "total_routers": [-1]}}
{"event_id": 2, "timestamp": "2025-11-09T16:27:59.956123", "event_type": "ROUTER_ADDED", "simulation_id": "20251109_162759", "router_id": -1, "data": {"router_id": 0, "total_routers": [-1, 0]}}
{"event_id": 3, "timestamp": "2025-11-09T16:27:59.956720", "event_type": "ROUTER_ADDED", "simulation_id": "20251109_162759", "router_id": -1, "data": {"router_id": 1, "total_routers": [-1, 0, 1]}}
{"event_id": 4, "timestamp": "2025-11-09T16:27:59.957075", "event_type": "ROUTER_ADDED", "simulation_id": "20251109_162759", "router_id": -1, "data": {"router_id": 2, "total_routers": [-1, 0, 1, 2]}}
{"event_id": 5, "timestamp": "2025-11-09T16:27:59.957387", "event_type": "ROUTER_ADDED", "simulation_id": "20251109_162759", "router_id": -1, "data": {"router_id": 3, "total_routers": [-1, 0, 1, 2, 3]}}
{"event_id": 6, "timestamp": "2025-11-09T16:27:59.957722", "event_type": "ROUTER_ADDED", "simulation_id": "20251109_162759", "router_id": -1, "data": {"router_id": 4, "total_routers": [-1, 0, 1, 2, 3, 4]}}
{"event_id": 7, "timestamp": "2025-11-09T16:27:59.958136", "event_type": "LINKS_CREATED", "simulation_id": "20251109_162759", "topology_type": "linear", "data": {"connections": [[0, -1], [-1, 0], [1, 0], [0, 1], [1, -1], [-1, 1], [2, 1], [1, 2], [2, -1], [-1, 2], [3, 2], [2, 3], [3, -1], [-1, 3], [4, 3], [3, 4], [4, -1], [-1, 4]], "total_links": 18}}
{"event_id": 8, "timestamp": "2025-11-09T16:27:59.958392", "event_type": "SIMULATION_READY", "simulation_id": "20251109_162759", "topology_type": "linear", "data": {"total_routers": 6, "total_links": 18}}
{"event_id": 9, "timestamp": "2025-11-09T16:27:59.959472", "event_type": "HELLO_SENT", "simulation_id": "20251109_162759", "data": {"message": {"message_id": "-1_1762684079.9592848_4686", "source_id": -1, "dest_id": null, "type": "HELLO", "data": {"sent_time": 1762684079.9592764, "neighbor_num": 0}, "timestamp": 1762684079.959284}, "from_router": -1, "to_neighbor": 0}}
{"event_id": 10, "timestamp": "2025-11-09T16:27:59.959936", "event_type": "HELLO_SENT", "simulation_id": "20251109_162759", "data": {"message": {"message_id": "-1_1762684079.9597857_6896", "source_id": -1, "dest_id": null, "type": "HELLO", "data": {"sent_time": 1762684079.959783, "neighbor_num": 1}, "timestamp": 1762684079.9597852}, "from_router": -1, "to_neighbor": 1}}
{"event_id": 11, "timestamp": "2025-11-09T16:27:59.960395", "event_type": "HELLO_SENT", "simulation_id": "20251109_162759", "data": {"message": {"message_id": "-1_1762684079.9602466_5818", "source_id": -1, "dest_id": null, "type": "HELLO", "data": {"sent_time": 1762684079.9602444, "neighbor_num": 2}, "timestamp": 1762684079.9602463}, "from_router": -1, "to_neighbor": 2}}
{"event_id": 12, "timestamp": "2025-11-09T16:27:59.960926", "event_type": "HELLO_SENT", "simulation_id": "20251109_162759", "data": {"message": {"message_id": "-1_1762684079.960772_4345", "source_id": -1, "dest_id": null, "type": "HELLO", "data": {"sent_time": 1762684079.96077, "neighbor_num": 3}, "timestamp": 1762684079.9607716}, "from_router": -1, "to_neighbor": 3}}
{"event_id": 13, "timestamp": "2025-11-09T16:27:59.961469", "event_type": "HELLO_SENT", "simulation_id": "20251109_162759", "data": {"message": {"message_id": "-1_1762684079.9613247_9653", "source_id": -1, "dest_id": null, "type": "HELLO", "data": {"sent_time": 1762684079.9613225, "neighbor_num": 4}, "timestamp": 1762684079.9613242}, "from_router": -1, "to_neighbor": 4}}
{"event_id": 14, "timestamp": "2025-11-09T16:27:59.962216", "event_type": "HELLO_SENT", "simulation_id": "20251109_162759", "data": {"message": {"message_id": "0_1762684079.9620802_1871", "source_id": 0, "dest_id": null, "type": "HELLO", "data": {"sent_time": 1762684079.962078, "neighbor_num": -1}, "timestamp": 1762684079.9620798}, "from_router": 0, "to_neighbor": -1}}
{"event_id": 15, "timestamp": "2025-11-09T16:27:59.962721", "event_type": "HELLO_SENT", "simulation_id": "20251109_162759", "data": {"message": {"message_id": "0_1762684079.96256_8370", "source_id": 0, "dest_id": null, "type": "HELLO", "data": {"sent_time": 1762684079.9625583, "neighbor_num": 1}, "timestamp": 1762684079.9625595}, "from_router": 0, "to_neighbor": 1}}
{"event_id": 16, "timestamp": "2025-11-09T16:27:59.963317", "event_type": "HELLO_SENT", "simulation_id": "20251109_162759", "data": {"message": {"message_id": "1_1762684079.963187_4640", "source_id": 1, "dest_id": null, "type": "HELLO", "data": {"sent_time": 1762684079.9631848, "neighbor_num": 0}, "timestamp": 1762684079.9631865}, "from_router": 1, "to_neighbor": 0}}
{"event_id": 17, "timestamp": "2025-11-09T16:27:59.963787", "event_type": "HELLO_SENT", "simulation_id": "20251109_162759", "data": {"message": {"message_id": "1_1762684079.9636307_7792", "source_id": 1, "dest_id": null, "type": "HELLO", "data": {"sent_time": 1762684079.963628, "neighbor_num": -1}, "timestamp": 1762684079.96363}, "from_router": 1, "to_neighbor": -1}}
{"event_id": 18, "timestamp": "2025-11-09T16:27:59.964333", "event_type": "HELLO_SENT", "simulation_id": "20251109_162759", "data": {"message": {"message_id": "1_1762684079.9641626_4070", "source_id": 1, "dest_id": null, "type": "HELLO", "data": {"sent_time": 1762684079.96416, "neighbor_num": 2}, "timestamp": 1762684079.9641623}, "from_router": 1, "to_neighbor": 2}}
{"event_id": 19, "timestamp": "2025-11-09T16:27:59.965041", "event_type": "HELLO_SENT", "simulation_id": "20251109_162759", "data": {"message": {"message_id": "2_1762684079.9648461_1276", "source_id": 2, "dest_id": null, "type": "HELLO", "data": {"sent_time": 1762684079.9648438, "neighbor_num": 1}, "timestamp": 1762684079.9648457}, "from_router": 2, "to_neighbor": 1}}
{"event_id": 20, "timestamp": "2025-11-09T16:27:59.965565", "event_type": "HELLO_SENT", "simulation_id": "20251109_162759", "data": {"message": {"message_id": "2_1762684079.9654095_4374", "source_id": 2, "dest_id": null, "type": "HELLO", "data": {"sent_time": 1762684079.9654078, "neighbor_num": -1}, "timestamp": 1762684079.9654093}, "from_router": 2, "to_neighbor": -1}}
{"event_id": 21, "timestamp": "2025-11-09T16:27:59.966051", "event_type": "HELLO_SENT", "simulation_id": "20251109_162759", "data": {"message": {"message_id": "2_1762684079.9658864_9623", "source_id": 2, "dest_id": null, "type": "HELLO", "data": {"sent_time": 1762684079.9658844, "neighbor_num": 3}, "timestamp": 1762684079.965886}, "from_router": 2, "to_neighbor": 3}}
{"event_id": 22, "timestamp": "2025-11-09T16:27:59.966754", "event_type": "HELLO_SENT", "simulation_id": "20251109_162759", "data": {"message": {"message_id": "3_1762684079.9665885_6732", "source_id": 3, "dest_id": null, "type": "HELLO", "data": {"sent_time": 1762684079.9665856, "neighbor_num": 2}, "timestamp": 1762684079.9665875}, "from_router": 3, "to_neighbor": 2}}
{"event_id": 23, "timestamp": "2025-11-09T16:27:59.967414", "event_type": "HELLO_SENT", "simulation_id": "20251109_162759", "data": {"message": {"message_id": "3_1762684079.9671967_7825", "source_id": 3, "dest_id": null, "type": "HELLO", "data": {"sent_time": 1762684079.9671934, "neighbor_num": -1}, "timestamp": 1762684079.9671962}, "from_router": 3, "to_neighbor": -1}}
{"event_id": 24, "timestamp": "2025-11-09T16:27:59.968085", "event_type": "HELLO_SENT", "simulation_id": "20251109_162759", "data": {"message": {"message_id": "3_1762684079.9678888_8515", "source_id": 3, "dest_id": null, "type": "HELLO", "data": {"sent_time": 1762684079.9678864, "neighbor_num": 4}, "timestamp": 1762684079.9678884}, "from_router": 3, "to_neighbor": 4}}
{"event_id": 25, "timestamp": "2025-11-09T16:27:59.968772", "event_type": "HELLO_SENT", "simulation_id": "20251109_162759", "data": {"message": {"message_id": "4_1762684079.968627_5805", "source_id": 4, "dest_id": null, "type": "HELLO", "data": {"sent_time": 1762684079.9686246, "neighbor_num": 3}, "timestamp": 1762684079.9686267}, "from_router": 4, "to_neighbor": 3}}
{"event_id": 26, "timestamp": "2025-11-09T16:27:59.969312", "event_type": "HELLO_SENT", "simulation_id": "20251109_162759", "data": {"message": {"message_id": "4_1762684079.96915_1073", "source_id": 4, "dest_id": null, "type": "HELLO", "data": {"sent_time": 1762684079.969148, "neighbor_num": -1}, "timestamp": 1762684079.9691496}, "from_router": 4, "to_neighbor": -1}}
{"event_id": 27, "timestamp": "2025-11-09T16:28:00.063508", "event_type": "MESSAGE_RECEIVED", "simulation_id": "20251109_162759", "data": {"message": {"message_id": "1_1762684079.963187_4640", "source_id": 1, "dest_id": null, "type": "HELLO", "data": {"sent_time": 1762684079.9631848, "neighbor_num": 0}, "timestamp": 1762684079.9631865}, "by_router": 1}}
{"event_id": 28, "timestamp": "2025-11-09T16:28:00.064211", "event_type": "HELLO_RECEIVED", "simulation_id": "20251109_162759", "router_id": 1, "data": {"from_router": 1, "current_hello_list": [1]}}
{"event_id": 29, "timestamp": "2025-11-09T16:28:00.064629", "event_type": "MESSAGE_RECEIVED", "simulation_id": "20251109_162759", "data": {"message": {"message_id": "1_1762684079.9636307_7792", "source_id": 1, "dest_id": null, "type": "HELLO", "data": {"sent_time": 1762684079.963628, "neighbor_num": -1}, "timestamp": 1762684079.96363}, "by_router": 1}}
{"event_id": 30, "timestamp": "2025-11-09T16:28:00.064959", "event_type": "MESSAGE_RECEIVED", "simulation_id": "20251109_162759", "data": {"message": {"message_id": "1_1762684079.9641626_4070", "source_id": 1, "dest_id": null, "type": "HELLO", "data": {"sent_time": 1762684079.96416, "neighbor_num": 2}, "timestamp": 1762684079.9641623}, "by_router": 1}}
{"event_id": 31, "timestamp": "2025-11-09T16:28:00.067070", "event_type": "MESSAGE_RECEIVED", "simulation_id": "20251109_162759", "data": {"message": {"message_id": "3_1762684079.9665885_6732", "source_id": 3, "dest_id": null, "type": "HELLO", "data": {"sent_time": 1762684079.9665856, "neighbor_num": 2}, "timestamp": 1762684079.9665875}, "by_router": 3}}
{"event_id": 32, "timestamp": "2025-11-09T16:28:00.067453", "event_type": "HELLO_RECEIVED", "simulation_id": "20251109_162759", "router_id": 3, "data": {"from_router": 3, "current_hello_list": [3]}}
{"event_id": 33, "timestamp": "2025-11-09T16:28:00.067850", "event_type": "MESSAGE_RECEIVED", "simulation_id": "20251109_162759", "data": {"message": {"message_id": "3_1762684079.9671967_7825", "source_id": 3, "dest_id": null, "type": "HELLO", "data": {"sent_time": 1762684079.9671934, "neighbor_num": -1}, "timestamp": 1762684079.9671962}, "by_router": 3}}
{"event_id": 34, "timestamp": "2025-11-09T16:28:00.069097", "event_type": "MESSAGE_RECEIVED", "simulation_id": "20251109_162759", "data": {"message": {"message_id": "4_1762684079.968627_5805", "source_id": 4, "dest_id": null, "type": "HELLO", "data": {"sent_time": 1762684079.9686246, "neighbor_num": 3}, "timestamp": 1762684079.9686267}, "by_router": 4}}
{"event_id": 35, "timestamp": "2025-11-09T16:28:00.069472", "event_type": "HELLO_RECEIVED", "simulation_id": "20251109_162759", "router_id": 4, "data": {"from_router": 4, "current_hello_list": [4]}}
{"event_id": 36, "timestamp": "2025-11-09T16:28:00.069865", "event_type": "MESSAGE_RECEIVED", "simulation_id": "20251109_162759", "data": {"message": {"message_id": "4_1762684079.96915_1073", "source_id": 4, "dest_id": null, "type": "HELLO", "data": {"sent_time": 1762684079.969148, "neighbor_num": -1}, "timestamp": 1762684079.9691496}, "by_router": 4}}
{"event_id": 37, "timestamp": "2025-11-09T16:28:00.159805", "event_type": "MESSAGE_RECEIVED", "simulation_id": "20251109_162759", "data": {"message": {"message_id": "-1_1762684079.9592848_4686", "source_id": -1, "dest_id": null, "type": "HELLO", "data": {"sent_time": 1762684079.9592764, "neighbor_num": 0}, "timestamp": 1762684079.959284}, "by_router": -1}}
{"event_id": 38, "timestamp": "2025-11-09T16:28:00.160552", "event_type": "HELLO_RECEIVED", "simulation_id": "20251109_162759", "router_id": -1, "data": {"from_router": -1, "current_hello_list": [-1]}}
{"event_id": 39, "timestamp": "2025-11-09T16:28:00.161062", "event_type": "MESSAGE_RECEIVED", "simulation_id": "20251109_162759", "data": {"message": {"message_id": "-1_1762684079.9597857_6896", "source_id": -1, "dest_id": null, "type": "HELLO", "data": {"sent_time": 1762684079.959783, "neighbor_num": 1}, "timestamp": 1762684079.9597852}, "by_router": -1}}
{"event_id": 40, "timestamp": "2025-11-09T16:28:00.161562", "event_type": "MESSAGE_RECEIVED", "simulation_id": "20251109_162759", "data": {"message": {"message_id": "-1_1762684079.9602466_5818", "source_id": -1, "dest_id": null, "type": "HELLO", "data": {"sent_time": 1762684079.9602444, "neighbor_num": 2}, "timestamp": 1762684079.9602463}, "by_router": -1}}
{"event_id": 41, "timestamp": "2025-11-09T16:28:00.161948", "event_type": "MESSAGE_RECEIVED", "simulation_id": "20251109_162759", "data": {"message": {"message_id": "-1_1762684079.960772_4345", "source_id": -1, "dest_id": null, "type": "HELLO", "data": {"sent_time": 1762684079.96077, "neighbor_num": 3}, "timestamp": 1762684079.9607716}, "by_router": -1}}
{"event_id": 42, "timestamp": "2025-11-09T16:28:00.162285", "event_type": "MESSAGE_RECEIVED", "simulation_id": "20251109_162759", "data": {"message": {"message_id": "-1_1762684079.9613247_9653", "source_id": -1, "dest_id": null, "type": "HELLO", "data": {"sent_time": 1762684079.9613225, "neighbor_num": 4}, "timestamp": 1762684079.9613242}, "by_router": -1}}
{"event_id": 43, "timestamp": "2025-11-09T16:28:00.162767", "event_type": "MESSAGE_RECEIVED", "simulation_id": "20251109_162759", "data": {"message": {"message_id": "0_1762684079.9620802_1871", "source_id": 0, "dest_id": null, "type": "HELLO", "data": {"sent_time": 1762684079.962078, "neighbor_num": -1}, "timestamp": 1762684079.9620798}, "by_router": 0}}
{"event_id": 44, "timestamp": "2025-11-09T16:28:00.163150", "event_type": "HELLO_RECEIVED", "simulation_id": "20251109_162759", "router_id": 0, "data": {"from_router": 0, "current_hello_list": [0]}}
{"event_id": 45, "timestamp": "2025-11-09T16:28:00.163532", "event_type": "MESSAGE_RECEIVED", "simulation_id": "20251109_162759", "data": {"message": {"message_id": "0_1762684079.96256_8370", "source_id": 0, "dest_id": null, "type": "HELLO", "data": {"sent_time": 1762684079.9625583, "neighbor_num": 1}, "timestamp": 1762684079.9625595}, "by_router": 0}}
{"event_id": 46, "timestamp": "2025-11-09T16:28:00.165066", "event_type": "MESSAGE_RECEIVED", "simulation_id": "20251109_162759", "data": {"message": {"message_id": "2_1762684079.9648461_1276", "source_id": 2, "dest_id": null, "type": "HELLO", "data": {"sent_time": 1762684079.9648438, "neighbor_num": 1}, "timestamp": 1762684079.9648457}, "by_router": 2}}
{"event_id": 47, "timestamp": "2025-11-09T16:28:00.165415", "event_type": "HELLO_RECEIVED", "simulation_id": "20251109_162759", "router_id": 2, "data": {"from_router": 2, "current_hello_list": [2]}}
{"event_id": 48, "timestamp": "2025-11-09T16:28:00.165833", "event_type": "MESSAGE_RECEIVED", "simulation_id": "20251109_162759", "data": {"message": {"message_id": "2_1762684079.9654095_4374", "source_id": 2, "dest_id": null, "type": "HELLO", "data": {"sent_time": 1762684079.9654078, "neighbor_num": -1}, "timestamp": 1762684079.9654093}, "by_router": 2}}
{"event_id": 49, "timestamp": "2025-11-09T16:28:00.166235", "event_type": "MESSAGE_RECEIVED", "simulation_id": "20251109_162759", "data": {"message": {"message_id": "2_1762684079.9658864_9623", "source_id": 2, "dest_id": null, "type": "HELLO", "data": {"sent_time": 1762684079.9658844, "neighbor_num": 3}, "timestamp": 1762684079.965886}, "by_router": 2}}
{"event_id": 50, "timestamp": "2025-11-09T16:28:00.168589", "event_type": "MESSAGE_RECEIVED", "simulation_id": "20251109_162759", "data": {"message": {"message_id": "3_1762684079.9678888_8515", "source_id": 3, "dest_id": null, "type": "HELLO", "data": {"sent_time": 1762684079.9678864, "neighbor_num": 4}, "timestamp": 1762684079.9678884}, "by_router": 3}}
{"event_id": 51, "timestamp": "2025-11-09T16:28:01.962453", "event_type": "NEIGHBORS_REQUEST_SENT", "simulation_id": "20251109_162759", "data": {"message": {"message_id": "-1_1762684081.962104_2399", "source_id": -1, "dest_id": 0, "type": "GET_NEIGHBORS", "data": null, "timestamp": 1762684081.962102}, "to_router": 0}}
{"event_id": 52, "timestamp": "2025-11-09T16:28:01.963227", "event_type": "NEIGHBORS_REQUEST_SENT", "simulation_id": "20251109_162759", "data": {"message": {"message_id": "-1_1762684081.9629884_3585", "source_id": -1, "dest_id": 1, "type": "GET_NEIGHBORS", "data": null, "timestamp": 1762684081.9629874}, "to_router": 1}}
{"event_id": 53, "timestamp": "2025-11-09T16:28:01.963879", "event_type": "NEIGHBORS_REQUEST_SENT", "simulation_id": "20251109_162759", "data": {"message": {"message_id": "-1_1762684081.9636397_4081", "source_id": -1, "dest_id": 2, "type": "GET_NEIGHBORS", "data": null, "timestamp": 1762684081.9636393}, "to_router": 2}}
{"event_id": 54, "timestamp": "2025-11-09T16:28:01.964370", "event_type": "NEIGHBORS_REQUEST_SENT", "simulation_id": "20251109_162759", "data": {"message": {"message_id": "-1_1762684081.9642076_1693", "source_id": -1, "dest_id": 3, "type": "GET_NEIGHBORS", "data": null, "timestamp": 1762684081.9642074}, "to_router": 3}}
{"event_id": 55, "timestamp": "2025-11-09T16:28:01.964820", "event_type": "NEIGHBORS_REQUEST_SENT", "simulation_id": "20251109_162759", "data": {"message": {"message_id": "-1_1762684081.9646764_5202", "source_id": -1, "dest_id": 4, "type": "GET_NEIGHBORS", "data": null, "timestamp": 1762684081.9646761}, "to_router": 4}}
{"event_id": 56, "timestamp": "2025-11-09T16:28:02.070817", "event_type": "MESSAGE_RECEIVED", "simulation_id": "20251109_162759", "data": {"message": {"message_id": "-1_1762684081.962104_2399", "source_id": -1, "dest_id": 0, "type": "GET_NEIGHBORS", "data": null, "timestamp": 1762684081.962102}, "by_router": -1}}
{"event_id": 57, "timestamp": "2025-11-09T16:28:02.071733", "event_type": "NEIGHBORS_INFO_SENT", "simulation_id": "20251109_162759", "data": {"message": {"message_id": "-1_1762684082.0717173_8186", "source_id": -1, "dest_id": -1, "type": "SET_NEIGHBORS", "data": [{"neighbor_id": -1, "transmission_time": 0.4126156621277317}], "timestamp": 1762684082.0717163}, "from_router": -1, "to_dr": -1, "neighbors": [{"neighbor_id": -1, "transmission_time": 0.4126156621277317}]}}
{"event_id": 58, "timestamp": "2025-11-09T16:28:02.072327", "event_type": "MESSAGE_RECEIVED", "simulation_id": "20251109_162759", "data": {"message": {"message_id": "-1_1762684081.9629884_3585", "source_id": -1, "dest_id": 1, "type": "GET_NEIGHBORS", "data": null, "timestamp": 1762684081.9629874}, "by_router": -1}}
{"event_id": 59, "timestamp": "2025-11-09T16:28:02.072751", "event_type": "NEIGHBORS_INFO_SENT", "simulation_id": "20251109_162759", "data": {"message": {"message_id": "-1_1762684082.07274_5455", "source_id": -1, "dest_id": -1, "type": "SET_NEIGHBORS", "data": [{"neighbor_id": -1, "transmission_time": 0.13170860906243465}], "timestamp": 1762684082.0727396}, "from_router": -1, "to_dr": -1, "neighbors": [{"neighbor_id": -1, "transmission_time": 0.13170860906243465}]}}
{"event_id": 60, "timestamp": "2025-11-09T16:28:02.073100", "event_type": "MESSAGE_RECEIVED", "simulation_id": "20251109_162759", "data": {"message": {"message_id": "-1_1762684081.9636397_4081", "source_id": -1, "dest_id": 2, "type": "GET_NEIGHBORS", "data": null, "timestamp": 1762684081.9636393}, "by_router": -1}}
{"event_id": 61, "timestamp": "2025-11-09T16:28:02.073425", "event_type": "NEIGHBORS_INFO_SENT", "simulation_id": "20251109_162759", "data": {"message": {"message_id": "-1_1762684082.0734177_1244", "source_id": -1, "dest_id": -1, "type": "SET_NEIGHBORS", "data": [{"neighbor_id": -1, "transmission_time": 0.16169952829008813}], "timestamp": 1762684082.0734174}, "from_router": -1, "to_dr": -1, "neighbors": [{"neighbor_id": -1, "transmission_time": 0.16169952829008813}]}}
{"event_id": 62, "timestamp": "2025-11-09T16:28:02.073750", "event_type": "MESSAGE_RECEIVED", "simulation_id": "20251109_162759", "data": {"message": {"message_id": "-1_1762684081.9642076_1693", "source_id": -1, "dest_id": 3, "type": "GET_NEIGHBORS", "data": null, "timestamp": 1762684081.9642074}, "by_router": -1}}
{"event_id": 63, "timestamp": "2025-11-09T16:28:02.074132", "event_type": "NEIGHBORS_INFO_SENT", "simulation_id": "20251109_162759", "data": {"message": {"message_id": "-1_1762684082.0741258_5056", "source_id": -1, "dest_id": -1, "type": "SET_NEIGHBORS", "data": [{"neighbor_id": -1, "transmission_time": 0.4376555788986549}], "timestamp": 1762684082.0741253}, "from_router": -1, "to_dr": -1, "neighbors": [{"neighbor_id": -1, "transmission_time": 0.4376555788986549}]}}
{"event_id": 64, "timestamp": "2025-11-09T16:28:02.074462", "event_type": "MESSAGE_RECEIVED", "simulation_id": "20251109_162759", "data": {"message": {"message_id": "-1_1762684081.9646764_5202", "source_id": -1, "dest_id": 4, "type": "GET_NEIGHBORS", "data": null, "timestamp": 1762684081.9646761}, "by_router": -1}}
{"event_id": 65, "timestamp": "2025-11-09T16:28:02.074783", "event_type": "NEIGHBORS_INFO_SENT", "simulation_id": "20251109_162759", "data": {"message": {"message_id": "-1_1762684082.0747764_4058", "source_id": -1, "dest_id": -1, "type": "SET_NEIGHBORS", "data": [{"neighbor_id": -1, "transmission_time": 0.4376152696111948}], "timestamp": 1762684082.0747762}, "from_router": -1, "to_dr": -1, "neighbors": [{"neighbor_id": -1, "transmission_time": 0.4376152696111948}]}}
{"event_id": 66, "timestamp": "2025-11-09T16:28:02.970212", "event_type": "TEST_DATA_TRANSFER_START", "simulation_id": "20251109_162759", "topology_type": "linear", "data": {}}
{"event_id": 67, "timestamp": "2025-11-09T16:28:02.970972", "event_type": "DATA_SEND_FAILED", "simulation_id": "20251109_162759", "router_id": 0, "data": {"destination": 4, "reason": "No path available"}}
{"event_id": 68, "timestamp": "2025-11-09T16:28:04.974377", "event_type": "TOPOLOGY_BROADCAST", "simulation_id": "20251109_162759", "topology_type": "linear", "data": {"topology": {"nodes": [-1, 0, 1, 2, 3, 4], "edges": []}, "recipients": [0, 1, 2, 3, 4]}}
{"event_id": 69, "timestamp": "2025-11-09T16:28:04.974905", "event_type": "DISCONNECT_SIMULATED", "simulation_id": "20251109_162759", "topology_type": "linear", "data": {"router1": 1, "router2": 2, "edge_removed": false, "topology_change_count": 1, "current_topology_edges": []}}
{"event_id": 71, "timestamp": "2025-11-09T16:28:06.976424", "event_type": "DATA_SEND_FAILED", "simulation_id": "20251109_162759", "router_id": 0, "data": {"destination": 4, "reason": "No path available"}}
{"event_id": 72, "timestamp": "2025-11-09T16:28:16.978163", "event_type": "SIMULATION_END", "simulation_id": "20251109_162759", "data": {}}
